[
  {
    "id":"gh_0",
    "title":"Senior Data Scientist",
    "company":"TechCorp",
    "location":"Remote",
    "description":"Looking for a data scientist with Python, SQL, and ML experience. Must know TensorFlow.",
    "skills":[
      "Python",
      "SQL",
      "Machine Learning",
      "TensorFlow"
    ],
    "posted_date":"2026-02-08",
    "source":"github_jobs",
    "salary_range":null,
    "experience_level":null
  },
  {
    "id":"gh_1",
    "title":"Senior Data Scientist",
    "company":"DataWorks",
    "location":"Remote",
    "description":"Looking for a data scientist with Python, SQL, and ML experience. Must know PyTorch.",
    "skills":[
      "Python",
      "SQL",
      "Machine Learning",
      "PyTorch"
    ],
    "posted_date":"2026-02-08",
    "source":"github_jobs",
    "salary_range":null,
    "experience_level":null
  },
  {
    "id":"gh_2",
    "title":"Senior Data Scientist",
    "company":"AIStartup",
    "location":"Remote",
    "description":"Looking for a data scientist with Python, SQL, and ML experience. Must know AWS.",
    "skills":[
      "Python",
      "SQL",
      "Machine Learning",
      "AWS"
    ],
    "posted_date":"2026-02-08",
    "source":"github_jobs",
    "salary_range":null,
    "experience_level":null
  },
  {
    "id":"gh_3",
    "title":"Senior Data Scientist",
    "company":"TechCorp",
    "location":"Remote",
    "description":"Looking for a data scientist with Python, SQL, and ML experience. Must know TensorFlow.",
    "skills":[
      "Python",
      "SQL",
      "Machine Learning",
      "TensorFlow"
    ],
    "posted_date":"2026-02-08",
    "source":"github_jobs",
    "salary_range":null,
    "experience_level":null
  },
  {
    "id":"gh_4",
    "title":"Senior Data Scientist",
    "company":"DataWorks",
    "location":"Remote",
    "description":"Looking for a data scientist with Python, SQL, and ML experience. Must know PyTorch.",
    "skills":[
      "Python",
      "SQL",
      "Machine Learning",
      "PyTorch"
    ],
    "posted_date":"2026-02-08",
    "source":"github_jobs",
    "salary_range":null,
    "experience_level":null
  },
  {
    "id":"gh_5",
    "title":"Senior Data Scientist",
    "company":"AIStartup",
    "location":"Remote",
    "description":"Looking for a data scientist with Python, SQL, and ML experience. Must know AWS.",
    "skills":[
      "Python",
      "SQL",
      "Machine Learning",
      "AWS"
    ],
    "posted_date":"2026-02-08",
    "source":"github_jobs",
    "salary_range":null,
    "experience_level":null
  },
  {
    "id":"gh_6",
    "title":"Senior Data Scientist",
    "company":"TechCorp",
    "location":"Remote",
    "description":"Looking for a data scientist with Python, SQL, and ML experience. Must know TensorFlow.",
    "skills":[
      "Python",
      "SQL",
      "Machine Learning",
      "TensorFlow"
    ],
    "posted_date":"2026-02-08",
    "source":"github_jobs",
    "salary_range":null,
    "experience_level":null
  },
  {
    "id":"gh_7",
    "title":"Senior Data Scientist",
    "company":"DataWorks",
    "location":"Remote",
    "description":"Looking for a data scientist with Python, SQL, and ML experience. Must know PyTorch.",
    "skills":[
      "Python",
      "SQL",
      "Machine Learning",
      "PyTorch"
    ],
    "posted_date":"2026-02-08",
    "source":"github_jobs",
    "salary_range":null,
    "experience_level":null
  },
  {
    "id":"gh_8",
    "title":"Senior Data Scientist",
    "company":"AIStartup",
    "location":"Remote",
    "description":"Looking for a data scientist with Python, SQL, and ML experience. Must know AWS.",
    "skills":[
      "Python",
      "SQL",
      "Machine Learning",
      "AWS"
    ],
    "posted_date":"2026-02-08",
    "source":"github_jobs",
    "salary_range":null,
    "experience_level":null
  },
  {
    "id":"gh_9",
    "title":"Senior Data Scientist",
    "company":"TechCorp",
    "location":"Remote",
    "description":"Looking for a data scientist with Python, SQL, and ML experience. Must know TensorFlow.",
    "skills":[
      "Python",
      "SQL",
      "Machine Learning",
      "TensorFlow"
    ],
    "posted_date":"2026-02-08",
    "source":"github_jobs",
    "salary_range":null,
    "experience_level":null
  },
  {
    "id":"gh_0",
    "title":"Senior Machine Learning Engineer",
    "company":"TechCorp",
    "location":"Remote",
    "description":"Looking for a machine learning engineer with Python, SQL, and ML experience. Must know TensorFlow.",
    "skills":[
      "Python",
      "SQL",
      "Machine Learning",
      "TensorFlow"
    ],
    "posted_date":"2026-02-08",
    "source":"github_jobs",
    "salary_range":null,
    "experience_level":null
  },
  {
    "id":"gh_1",
    "title":"Senior Machine Learning Engineer",
    "company":"DataWorks",
    "location":"Remote",
    "description":"Looking for a machine learning engineer with Python, SQL, and ML experience. Must know PyTorch.",
    "skills":[
      "Python",
      "SQL",
      "Machine Learning",
      "PyTorch"
    ],
    "posted_date":"2026-02-08",
    "source":"github_jobs",
    "salary_range":null,
    "experience_level":null
  },
  {
    "id":"gh_2",
    "title":"Senior Machine Learning Engineer",
    "company":"AIStartup",
    "location":"Remote",
    "description":"Looking for a machine learning engineer with Python, SQL, and ML experience. Must know AWS.",
    "skills":[
      "Python",
      "SQL",
      "Machine Learning",
      "AWS"
    ],
    "posted_date":"2026-02-08",
    "source":"github_jobs",
    "salary_range":null,
    "experience_level":null
  },
  {
    "id":"gh_3",
    "title":"Senior Machine Learning Engineer",
    "company":"TechCorp",
    "location":"Remote",
    "description":"Looking for a machine learning engineer with Python, SQL, and ML experience. Must know TensorFlow.",
    "skills":[
      "Python",
      "SQL",
      "Machine Learning",
      "TensorFlow"
    ],
    "posted_date":"2026-02-08",
    "source":"github_jobs",
    "salary_range":null,
    "experience_level":null
  },
  {
    "id":"gh_4",
    "title":"Senior Machine Learning Engineer",
    "company":"DataWorks",
    "location":"Remote",
    "description":"Looking for a machine learning engineer with Python, SQL, and ML experience. Must know PyTorch.",
    "skills":[
      "Python",
      "SQL",
      "Machine Learning",
      "PyTorch"
    ],
    "posted_date":"2026-02-08",
    "source":"github_jobs",
    "salary_range":null,
    "experience_level":null
  },
  {
    "id":"gh_5",
    "title":"Senior Machine Learning Engineer",
    "company":"AIStartup",
    "location":"Remote",
    "description":"Looking for a machine learning engineer with Python, SQL, and ML experience. Must know AWS.",
    "skills":[
      "Python",
      "SQL",
      "Machine Learning",
      "AWS"
    ],
    "posted_date":"2026-02-08",
    "source":"github_jobs",
    "salary_range":null,
    "experience_level":null
  },
  {
    "id":"gh_6",
    "title":"Senior Machine Learning Engineer",
    "company":"TechCorp",
    "location":"Remote",
    "description":"Looking for a machine learning engineer with Python, SQL, and ML experience. Must know TensorFlow.",
    "skills":[
      "Python",
      "SQL",
      "Machine Learning",
      "TensorFlow"
    ],
    "posted_date":"2026-02-08",
    "source":"github_jobs",
    "salary_range":null,
    "experience_level":null
  },
  {
    "id":"gh_7",
    "title":"Senior Machine Learning Engineer",
    "company":"DataWorks",
    "location":"Remote",
    "description":"Looking for a machine learning engineer with Python, SQL, and ML experience. Must know PyTorch.",
    "skills":[
      "Python",
      "SQL",
      "Machine Learning",
      "PyTorch"
    ],
    "posted_date":"2026-02-08",
    "source":"github_jobs",
    "salary_range":null,
    "experience_level":null
  },
  {
    "id":"gh_8",
    "title":"Senior Machine Learning Engineer",
    "company":"AIStartup",
    "location":"Remote",
    "description":"Looking for a machine learning engineer with Python, SQL, and ML experience. Must know AWS.",
    "skills":[
      "Python",
      "SQL",
      "Machine Learning",
      "AWS"
    ],
    "posted_date":"2026-02-08",
    "source":"github_jobs",
    "salary_range":null,
    "experience_level":null
  },
  {
    "id":"gh_9",
    "title":"Senior Machine Learning Engineer",
    "company":"TechCorp",
    "location":"Remote",
    "description":"Looking for a machine learning engineer with Python, SQL, and ML experience. Must know TensorFlow.",
    "skills":[
      "Python",
      "SQL",
      "Machine Learning",
      "TensorFlow"
    ],
    "posted_date":"2026-02-08",
    "source":"github_jobs",
    "salary_range":null,
    "experience_level":null
  },
  {
    "id":"li_0",
    "title":"Senior Data Scientist",
    "company":"Company_0",
    "location":"Remote",
    "description":"Seeking a data scientist with experience in various technologies.",
    "skills":[
      "Python",
      "SQL",
      "Machine Learning"
    ],
    "posted_date":"2026-02-01",
    "source":"linkedin_simulated",
    "salary_range":"$80,000-$120,000",
    "experience_level":"Entry"
  },
  {
    "id":"li_1",
    "title":"Mid-level Ml Engineer",
    "company":"Company_1",
    "location":"San Francisco, CA",
    "description":"Seeking a ml engineer with experience in various technologies.",
    "skills":[
      "Python",
      "Docker",
      "AWS",
      "MLOps"
    ],
    "posted_date":"2026-02-02",
    "source":"linkedin_simulated",
    "salary_range":"$85,000-$130,000",
    "experience_level":"Mid"
  },
  {
    "id":"li_2",
    "title":"Junior Data Engineer",
    "company":"Company_2",
    "location":"New York, NY",
    "description":"Seeking a data engineer with experience in various technologies.",
    "skills":[
      "SQL",
      "Python",
      "Spark",
      "AWS",
      "Airflow"
    ],
    "posted_date":"2026-02-03",
    "source":"linkedin_simulated",
    "salary_range":"$90,000-$140,000",
    "experience_level":"Senior"
  },
  {
    "id":"li_3",
    "title":"Senior Backend Engineer",
    "company":"Company_3",
    "location":"Remote",
    "description":"Seeking a backend engineer with experience in various technologies.",
    "skills":[
      "Python",
      "FastAPI",
      "Docker",
      "PostgreSQL",
      "AWS",
      "Redis"
    ],
    "posted_date":"2026-02-04",
    "source":"linkedin_simulated",
    "salary_range":"$95,000-$150,000",
    "experience_level":"Entry"
  },
  {
    "id":"li_4",
    "title":"Mid-level Data Scientist",
    "company":"Company_4",
    "location":"San Francisco, CA",
    "description":"Seeking a data scientist with experience in various technologies.",
    "skills":[
      "Python",
      "SQL",
      "Machine Learning"
    ],
    "posted_date":"2026-02-05",
    "source":"linkedin_simulated",
    "salary_range":"$100,000-$160,000",
    "experience_level":"Mid"
  },
  {
    "id":"li_5",
    "title":"Junior Ml Engineer",
    "company":"Company_5",
    "location":"New York, NY",
    "description":"Seeking a ml engineer with experience in various technologies.",
    "skills":[
      "Python",
      "Docker",
      "AWS",
      "MLOps"
    ],
    "posted_date":"2026-02-06",
    "source":"linkedin_simulated",
    "salary_range":"$105,000-$170,000",
    "experience_level":"Senior"
  },
  {
    "id":"li_6",
    "title":"Senior Data Engineer",
    "company":"Company_6",
    "location":"Remote",
    "description":"Seeking a data engineer with experience in various technologies.",
    "skills":[
      "SQL",
      "Python",
      "Spark",
      "AWS",
      "Airflow"
    ],
    "posted_date":"2026-02-07",
    "source":"linkedin_simulated",
    "salary_range":"$110,000-$180,000",
    "experience_level":"Entry"
  },
  {
    "id":"li_7",
    "title":"Mid-level Backend Engineer",
    "company":"Company_7",
    "location":"San Francisco, CA",
    "description":"Seeking a backend engineer with experience in various technologies.",
    "skills":[
      "Python",
      "FastAPI",
      "Docker",
      "PostgreSQL",
      "AWS",
      "Redis"
    ],
    "posted_date":"2026-02-08",
    "source":"linkedin_simulated",
    "salary_range":"$115,000-$190,000",
    "experience_level":"Mid"
  },
  {
    "id":"li_8",
    "title":"Junior Data Scientist",
    "company":"Company_8",
    "location":"New York, NY",
    "description":"Seeking a data scientist with experience in various technologies.",
    "skills":[
      "Python",
      "SQL",
      "Machine Learning"
    ],
    "posted_date":"2026-02-09",
    "source":"linkedin_simulated",
    "salary_range":"$120,000-$200,000",
    "experience_level":"Senior"
  },
  {
    "id":"li_9",
    "title":"Senior Ml Engineer",
    "company":"Company_9",
    "location":"Remote",
    "description":"Seeking a ml engineer with experience in various technologies.",
    "skills":[
      "Python",
      "Docker",
      "AWS",
      "MLOps"
    ],
    "posted_date":"2026-02-10",
    "source":"linkedin_simulated",
    "salary_range":"$125,000-$210,000",
    "experience_level":"Entry"
  },
  {
    "id":"li_10",
    "title":"Mid-level Data Engineer",
    "company":"Company_0",
    "location":"San Francisco, CA",
    "description":"Seeking a data engineer with experience in various technologies.",
    "skills":[
      "SQL",
      "Python",
      "Spark",
      "AWS",
      "Airflow"
    ],
    "posted_date":"2026-02-11",
    "source":"linkedin_simulated",
    "salary_range":"$130,000-$220,000",
    "experience_level":"Mid"
  },
  {
    "id":"li_11",
    "title":"Junior Backend Engineer",
    "company":"Company_1",
    "location":"New York, NY",
    "description":"Seeking a backend engineer with experience in various technologies.",
    "skills":[
      "Python",
      "FastAPI",
      "Docker",
      "PostgreSQL",
      "AWS",
      "Redis"
    ],
    "posted_date":"2026-02-12",
    "source":"linkedin_simulated",
    "salary_range":"$135,000-$230,000",
    "experience_level":"Senior"
  },
  {
    "id":"li_12",
    "title":"Senior Data Scientist",
    "company":"Company_2",
    "location":"Remote",
    "description":"Seeking a data scientist with experience in various technologies.",
    "skills":[
      "Python",
      "SQL",
      "Machine Learning"
    ],
    "posted_date":"2026-02-13",
    "source":"linkedin_simulated",
    "salary_range":"$140,000-$240,000",
    "experience_level":"Entry"
  },
  {
    "id":"li_13",
    "title":"Mid-level Ml Engineer",
    "company":"Company_3",
    "location":"San Francisco, CA",
    "description":"Seeking a ml engineer with experience in various technologies.",
    "skills":[
      "Python",
      "Docker",
      "AWS",
      "MLOps"
    ],
    "posted_date":"2026-02-14",
    "source":"linkedin_simulated",
    "salary_range":"$145,000-$250,000",
    "experience_level":"Mid"
  },
  {
    "id":"li_14",
    "title":"Junior Data Engineer",
    "company":"Company_4",
    "location":"New York, NY",
    "description":"Seeking a data engineer with experience in various technologies.",
    "skills":[
      "SQL",
      "Python",
      "Spark",
      "AWS",
      "Airflow"
    ],
    "posted_date":"2026-02-15",
    "source":"linkedin_simulated",
    "salary_range":"$150,000-$260,000",
    "experience_level":"Senior"
  },
  {
    "id":"li_15",
    "title":"Senior Backend Engineer",
    "company":"Company_5",
    "location":"Remote",
    "description":"Seeking a backend engineer with experience in various technologies.",
    "skills":[
      "Python",
      "FastAPI",
      "Docker",
      "PostgreSQL",
      "AWS",
      "Redis"
    ],
    "posted_date":"2026-02-16",
    "source":"linkedin_simulated",
    "salary_range":"$155,000-$270,000",
    "experience_level":"Entry"
  },
  {
    "id":"li_16",
    "title":"Mid-level Data Scientist",
    "company":"Company_6",
    "location":"San Francisco, CA",
    "description":"Seeking a data scientist with experience in various technologies.",
    "skills":[
      "Python",
      "SQL",
      "Machine Learning"
    ],
    "posted_date":"2026-02-17",
    "source":"linkedin_simulated",
    "salary_range":"$160,000-$280,000",
    "experience_level":"Mid"
  },
  {
    "id":"li_17",
    "title":"Junior Ml Engineer",
    "company":"Company_7",
    "location":"New York, NY",
    "description":"Seeking a ml engineer with experience in various technologies.",
    "skills":[
      "Python",
      "Docker",
      "AWS",
      "MLOps"
    ],
    "posted_date":"2026-02-18",
    "source":"linkedin_simulated",
    "salary_range":"$165,000-$290,000",
    "experience_level":"Senior"
  },
  {
    "id":"li_18",
    "title":"Senior Data Engineer",
    "company":"Company_8",
    "location":"Remote",
    "description":"Seeking a data engineer with experience in various technologies.",
    "skills":[
      "SQL",
      "Python",
      "Spark",
      "AWS",
      "Airflow"
    ],
    "posted_date":"2026-02-19",
    "source":"linkedin_simulated",
    "salary_range":"$170,000-$300,000",
    "experience_level":"Entry"
  },
  {
    "id":"li_19",
    "title":"Mid-level Backend Engineer",
    "company":"Company_9",
    "location":"San Francisco, CA",
    "description":"Seeking a backend engineer with experience in various technologies.",
    "skills":[
      "Python",
      "FastAPI",
      "Docker",
      "PostgreSQL",
      "AWS",
      "Redis"
    ],
    "posted_date":"2026-02-20",
    "source":"linkedin_simulated",
    "salary_range":"$175,000-$310,000",
    "experience_level":"Mid"
  }
]